ogmios/__about__.py
ogmios/__init__.py
ogmios/client.py
ogmios/datatypes.py
ogmios/errors.py
ogmios/logger.py
ogmios/response_handler.py
ogmios/utils.py
ogmios/chainsync/FindIntersection.py
ogmios/chainsync/NextBlock.py
ogmios/chainsync/__init__.py
ogmios/mempool/AcquireMempool.py
ogmios/mempool/HasTransaction.py
ogmios/mempool/NextTransaction.py
ogmios/mempool/ReleaseMempool.py
ogmios/mempool/SizeOfMempool.py
ogmios/mempool/__init__.py
ogmios/model/BaseModelNoException.py
ogmios/model/README.md
ogmios/model/cardano.json
ogmios/model/cardano_model.py
ogmios/model/model_map.py
ogmios/model/ogmios.json
ogmios/model/ogmios_model.py
ogmios/statequery/AcquireLedgerState.py
ogmios/statequery/QueryBlockHeight.py
ogmios/statequery/QueryConstitution.py
ogmios/statequery/QueryConstitutionalCommittee.py
ogmios/statequery/QueryEpoch.py
ogmios/statequery/QueryEraStart.py
ogmios/statequery/QueryEraSummaries.py
ogmios/statequery/QueryGenesisConfiguration.py
ogmios/statequery/QueryLedgerTip.py
ogmios/statequery/QueryLiveStakeDistribution.py
ogmios/statequery/QueryNetworkTip.py
ogmios/statequery/QueryProjectedRewards.py
ogmios/statequery/QueryProposedProtocolParameters.py
ogmios/statequery/QueryProtocolParameters.py
ogmios/statequery/QueryRewardAccountSummaries.py
ogmios/statequery/QueryRewardsProvenance.py
ogmios/statequery/QueryStakePools.py
ogmios/statequery/QueryStartTime.py
ogmios/statequery/QueryTreasuryAndReserves.py
ogmios/statequery/QueryUtxo.py
ogmios/statequery/__init__.py
ogmios/txsubmit/EvaluateTransaction.py
ogmios/txsubmit/SubmitTransaction.py
ogmios/txsubmit/__init__.py
ogmios-1.4.1.dist-info/METADATA
ogmios-1.4.1.dist-info/WHEEL
ogmios-1.4.1.dist-info/licenses/LICENSE.txt
ogmios-1.4.1.dist-info/RECORD
