Metadata-Version: 2.4
Name: ogmios
Version: 1.4.1
Summary: Ogmios is a lightweight bridge interface for cardano-node. It offers a WebSockets API that enables local clients to speak Ouroboros' mini-protocols via JSON/RPC. ogmios-python is an Ogmios client written in Python designed for ease of use.
Project-URL: Documentation, https://ogmios-python.readthedocs.io
Project-URL: Issues, https://gitlab.com/viperscience/ogmios-python/-/issues
Project-URL: Source, https://gitlab.com/viperscience/ogmios-python
Author-email: Willie Marchetto <willie@viperscience.com>, Dylan Crocker <dylan@viperscience.com>
License-File: LICENSE.txt
Classifier: Development Status :: 4 - Beta
Classifier: Programming Language :: Python
Classifier: Programming Language :: Python :: 3.8
Classifier: Programming Language :: Python :: 3.9
Classifier: Programming Language :: Python :: 3.10
Classifier: Programming Language :: Python :: 3.11
Classifier: Programming Language :: Python :: 3.12
Classifier: Programming Language :: Python :: Implementation :: CPython
Classifier: Programming Language :: Python :: Implementation :: PyPy
Requires-Python: >=3.8
Requires-Dist: cachetools
Requires-Dist: cardano-tools
Requires-Dist: coloredlogs
Requires-Dist: orjson
Requires-Dist: pydantic>=2.0
Requires-Dist: setuptools>=78.1.0
Requires-Dist: websockets
Provides-Extra: dev
Requires-Dist: black; extra == 'dev'
Requires-Dist: datamodel-code-generator; extra == 'dev'
Requires-Dist: flake8-pyproject; extra == 'dev'
Requires-Dist: isort; extra == 'dev'
Requires-Dist: sphinx; extra == 'dev'
Requires-Dist: sphinx-rtd-theme; extra == 'dev'
Provides-Extra: testing
Requires-Dist: coverage[toml]>=6.5; extra == 'testing'
Requires-Dist: pycardano; extra == 'testing'
Requires-Dist: pytest; extra == 'testing'
